Lab02/testbench_1.sv
// Testbench for 1 -bit adder
`include "design.sv"
module testbench ;
    reg a ,b , cin ;
    wire sum , cout ;
    onebitFullAdder dut (a ,b , cin , sum , cout ) ;
        always
            begin
                #10 b =~ b ;
            end
        always
            begin
                #20 a =~ a ;
            end
        initial
            begin
                $dumpfile ("dump.vcd") ; $dumpvars ;
                a = 0;
                b = 0;
                cin =0;
                #80 cin =1;
                #160 $finish ;
            end
endmodule
/*
module testbench ;
  reg [3:0] a, b;
    reg cin ;
  wire [3:0] sum;
    wire cout ;
    
    four_onebitFullAdder dut (a ,b , cin , sum , cout ) ;
        always
            begin
                #10 a [0] = ~ a [0];
            end
        always
            begin
                #20 a [1] = ~ a [1];
            end
        always
            begin
                #40 a [2] = ~ a [2];
            end
        always
            begin
                #80 a [3] = ~ a [3];
            end
        initial
        begin
            $dumpfile ("dump.vcd") ;
          $dumpvars (0 ,testbench ) ;
            a [0] = 0;
            a [1] = 0;
            a [2] = 0;
            a [3] = 0;
            b [0] = 0;
            b [1] = 0;
            b [2] = 0;
            b [3] = 0;
            cin = 0;
            #40 b [3] = 1; b [2] = 0; b [3] = 0; b [3] = 1; //b=4 ’ b1001
            #40 b [3] = 0; b [2] = 1; b [3] = 1; b [3] = 1; //b=4 ’ b0111
            #40 b [3] = 0; b [2] = 0; b [3] = 0; b [3] = 0; //b=4 ’ b0111
            cin = 1;
            #160 $finish ;
        end
endmodule
*/

Lab02/design.sv
// AND Module
module AND ( input a , input b , output reg c ) ;
always@ ( a or b )
    begin
        c = a & b ;
    end
endmodule

// NOT Module
module NOT ( input a , output reg b ) ;
    always @(a) begin
        b=~a;
    end
endmodule

// OR Module
module OR ( input a , input b , output reg c );
    always @(a or b) begin
        c=a|b;
    end
endmodule

// XOR Module
module XOR ( input a , input b , output reg c ) ;
    always @(a or b) begin
        c=a^b;
    end
endmodule

//1 -bit Full Adder
module onebitFullAdder ( 
    input a , 
    input b , 
    input cin , 
    output wire sum ,
    output wire cout ) ;

    wire bXc;

    //SUM
    XOR X0(
        .a  (b),
        .b  (cin),
        .c  (bXc)
    );
    XOR X1(
        .a  (a),
        .b  (bXc),
        .c  (sum)
    );

    wire ab,bc,ac,x;
    //CARRY
    AND A0(
        .a  (a),
        .b  (b),
        .c  (ab)
    );
    AND A1(
        .a  (b),
        .b  (cin),
        .c  (bc)
    );
    AND A2(
        .a  (a),
        .b  (cin),
        .c  (ac)
    );

    OR O0(
        .a  (ab),
        .b  (bc),
        .c  (x)
    );

    OR O1(
        .a  (x),
        .b  (ac),
        .c  (cout)
    );

endmodule

// //4 -bit Adder comprised of cascaded 1 -bit Full Adders
// module four_onebitFullAdder ( input a [3:0] , input b [3:0] , input cin ,
// output reg sum [3:0] , output reg cout ) ;
// // fill out this module using the onebitFullAdder module
// endmodule

Lab02/dump.vcd
$date
	Tue Apr 13 00:12:54 2021
$end
$version
	Icarus Verilog
$end
$timescale
	1s
$end
$scope module NOT $end
$var wire 1 ! a $end
$var reg 1 " b $end
$upscope $end
$scope module testbench $end
$var wire 1 # sum $end
$var wire 1 $ cout $end
$var reg 1 % a $end
$var reg 1 & b $end
$var reg 1 ' cin $end
$scope module dut $end
$var wire 1 % a $end
$var wire 1 & b $end
$var wire 1 ' cin $end
$var wire 1 ( x $end
$var wire 1 # sum $end
$var wire 1 $ cout $end
$var wire 1 ) bc $end
$var wire 1 * bXc $end
$var wire 1 + ac $end
$var wire 1 , ab $end
$scope module A0 $end
$var wire 1 % a $end
$var wire 1 & b $end
$var reg 1 , c $end
$upscope $end
$scope module A1 $end
$var wire 1 & a $end
$var wire 1 ' b $end
$var reg 1 ) c $end
$upscope $end
$scope module A2 $end
$var wire 1 % a $end
$var wire 1 ' b $end
$var reg 1 + c $end
$upscope $end
$scope module O0 $end
$var wire 1 , a $end
$var wire 1 ) b $end
$var reg 1 ( c $end
$upscope $end
$scope module O1 $end
$var wire 1 ( a $end
$var wire 1 + b $end
$var reg 1 $ c $end
$upscope $end
$scope module X0 $end
$var wire 1 & a $end
$var wire 1 ' b $end
$var reg 1 * c $end
$upscope $end
$scope module X1 $end
$var wire 1 % a $end
$var wire 1 * b $end
$var reg 1 # c $end
$upscope $end
$upscope $end
$upscope $end
$enddefinitions $end
#0
$dumpvars
0,
0+
0*
0)
0(
0'
0&
0%
0$
0#
x"
z!
$end
#10
1#
1*
1&
#20
0*
1#
0&
1%
#30
1$
1(
0#
1,
1*
1&
#40
0$
0(
0*
0,
0#
0&
0%
#50
1#
1*
1&
#60
0*
1#
0&
1%
#70
1$
1(
0#
1,
1*
1&
#80
0$
0(
0,
1#
0&
0%
1'
#90
1$
0#
1(
0*
1)
1&
#100
0(
0)
1*
1+
0#
0&
1%
#110
1#
1(
1,
0*
1)
1&
#120
0$
0(
0)
1*
0,
0+
1#
0&
0%
#130
1$
0#
1(
0*
1)
1&
#140
0(
0)
1*
1+
0#
0&
1%
#150
1#
1(
1,
0*
1)
1&
#160
0$
0(
0)
1*
0,
0+
1#
0&
0%
#170
1$
0#
1(
0*
1)
1&
#180
0(
0)
1*
1+
0#
0&
1%
#190
1#
1(
1,
0*
1)
1&
#200
0$
0(
0)
1*
0,
0+
1#
0&
0%
#210
1$
0#
1(
0*
1)
1&
#220
0(
0)
1*
1+
0#
0&
1%
#230
1#
1(
1,
0*
1)
1&
#240
0$
0(
0)
1*
0,
0+
1#
0&
0%
